batch_ida/__init__.py
batch_ida/bi_analyzer.py
batch_ida/bi_bindiff.py
batch_ida/bi_dircmp.py
batch_ida/bi_ida.py
batch_ida/bi_singleanalyzer.py
batch_ida-0.1.7.dist-info/LICENSE
batch_ida-0.1.7.dist-info/METADATA
batch_ida-0.1.7.dist-info/WHEEL
batch_ida-0.1.7.dist-info/RECORD
