Metadata-Version: 2.3
Name: batch-ida
Version: 0.1.7
Summary: A python library for generate ida pro files in batch mode & compare executable files use bindiff in batch mode.
License: MIT
Author: ZhengZH
Author-email: 41407837+chnzzh@users.noreply.github.com
Requires-Python: >=3.7,<4.0
Classifier: License :: OSI Approved :: MIT License
Classifier: Programming Language :: Python :: 3
Classifier: Programming Language :: Python :: 3.7
Classifier: Programming Language :: Python :: 3.8
Classifier: Programming Language :: Python :: 3.9
Classifier: Programming Language :: Python :: 3.10
Classifier: Programming Language :: Python :: 3.11
Classifier: Programming Language :: Python :: 3.12
Classifier: Programming Language :: Python :: 3.13
Project-URL: Bug Tracker, https://github.com/chnzzh/batch-ida/issues
Project-URL: Repository, https://github.com/chnzzh/batch-ida
